fantiadl/__init__.py
fantiadl/__main__.py
fantiadl/__version__.py
fantiadl/db.py
fantiadl/fantiadl.py
fantiadl/models.py
fantiadl/version.py
fantiadl-2.0.4.dist-info/LICENSE
fantiadl-2.0.4.dist-info/METADATA
fantiadl-2.0.4.dist-info/WHEEL
fantiadl-2.0.4.dist-info/entry_points.txt
fantiadl-2.0.4.dist-info/top_level.txt
fantiadl-2.0.4.dist-info/RECORD
