Metadata-Version: 2.1
Name: fantiadl
Version: 2.0.4
Summary: Download posts and media from Fantia
Home-page: https://github.com/bitbybyte/fantiadl
Author: bitto
License: MIT
Platform: UNKNOWN
Classifier: Programming Language :: Python
Classifier: Programming Language :: Python :: 3
Classifier: License :: OSI Approved :: MIT License
Classifier: Topic :: Internet :: WWW/HTTP
Requires-Python: >=3.0
License-File: LICENSE
Requires-Dist: beautifulsoup4
Requires-Dist: requests
